{
  "state" : {
    "retrievers" : [ "treebankRetriever" ]
  },

  "MainCtrl" : {
    "template"  : "templates/main2.html",
    "plugins" : {
      "text" : {
        "name" : "text",
        "main" : true,
        "template"  : "templates/text2.html"
      },
      "depTree" : {
        "name" : "depTree",
        "main" : true,
        "template" : "templates/dep_tree.html"
      },
      "history" : {
        "name" : "history",
        "listener" : true,
        "maxSize" : 5,
        "template" : "templates/history.html"
      }
    }
  }
}

