{
  "nested" : {
    "SBS" : {
      "short" : "SBV",
      "long" : "substantive",
      "nestedDependency" : true,
      "sections" : "1021-1029",
      "fileUrl" : "./static/configs/sg/sg_labels/cases.json"
    },
    "PRON" : {
      "short" : "PRON",
      "long" : "pronominal"
    },
    "NORM" : {
      "short" : "NORM",
      "long" : "normal"
    },
    "VRB" : {
      "short" : "VRB",
      "long" : "verbal"
    },
    "IDK" : {
      "short" : "IDK",
      "long" : "I don't know"
    }
  }
}
